{
  "race_type_priors": {
    "large_field_dirt_route": {
      "favorite_soften": 0.9,
      "mid_price_boost": 1.08,
      "longshot_boost": 1.03
    },
    "small_field_chalk": {
      "favorite_soften": 1.0,
      "mid_price_boost": 1.0,
      "longshot_boost": 1.0
    }
  },
  "field_size_priors": {
    "6-7": { "favoriteWinRate": 0.38 },
    "8-10": { "favoriteWinRate": 0.32 },
    "11-14": { "favoriteWinRate": 0.25 },
    "15+": { "favoriteWinRate": 0.18 }
  },
  "odds_rank": {
    "1": 0.94,
    "2": 1.0,
    "3": 1.02,
    "4-6": 1.08,
    "7+": 0.9
  },
  "race_type": {
    "turf_sprint": { "chaos": 1.2 },
    "maiden": { "chaos": 1.25 },
    "derby": { "chaos": 1.35 },
    "default": { "chaos": 1.0 }
  }
}
